README.md
flask_celery.py
setup.py
Flask_Celery_Helper.egg-info/PKG-INFO
Flask_Celery_Helper.egg-info/SOURCES.txt
Flask_Celery_Helper.egg-info/dependency_links.txt
Flask_Celery_Helper.egg-info/not-zip-safe
Flask_Celery_Helper.egg-info/requires.txt
Flask_Celery_Helper.egg-info/top_level.txt